tortoise_fastapi_crud/__init__.py
tortoise_fastapi_crud/_version.py
tortoise_fastapi_crud/core/__init__.py
tortoise_fastapi_crud/core/_types.py
tortoise_fastapi_crud/core/_utils.py
tortoise_fastapi_crud/core/tortoise.py
tortoise_fastapi_crud/py.typed
tortoise_fastapi_crudrouter-0.2.3.dist-info/LICENSE
tortoise_fastapi_crudrouter-0.2.3.dist-info/METADATA
tortoise_fastapi_crudrouter-0.2.3.dist-info/WHEEL
tortoise_fastapi_crudrouter-0.2.3.dist-info/RECORD
