Metadata-Version: 2.3
Name: tortoise-fastapi-crudrouter
Version: 0.2.3
Summary: A dynamic FastAPI router that automatically creates CRUD routes for your models
License: MIT
Keywords: fastapi,tortoise,crud,restful,routing,generator,crudrouter
Author: Dybfuo
Author-email: mail@fincubes.ru
Requires-Python: >=3.11
Classifier: Development Status :: 4 - Beta
Classifier: Environment :: Web Environment
Classifier: Framework :: AsyncIO
Classifier: Intended Audience :: Developers
Classifier: Intended Audience :: Information Technology
Classifier: Intended Audience :: System Administrators
Classifier: License :: OSI Approved :: MIT License
Classifier: Operating System :: OS Independent
Classifier: Programming Language :: Python :: 3
Classifier: Programming Language :: Python :: 3.11
Classifier: Programming Language :: Python :: 3.12
Classifier: Programming Language :: Python :: 3.13
Classifier: Programming Language :: Python :: 3 :: Only
Classifier: Programming Language :: Python :: 3.10
Classifier: Programming Language :: Python :: 3.7
Classifier: Programming Language :: Python :: 3.8
Classifier: Programming Language :: Python :: 3.9
Classifier: Topic :: Internet :: WWW/HTTP :: HTTP Servers
Classifier: Typing :: Typed
Requires-Dist: fastapi (>=0.116.1,<0.117.0)
Requires-Dist: tortoise-orm[asyncpg] (>=0.25.1,<0.26.0)
Project-URL: Documentation, https://fastapi-crudrouter.awtkns.com/
Project-URL: Homepage, https://github.com/awtkns/fastapi-crudrouter
Project-URL: Repository, https://github.com/awtkns/fastapi-crudrouter
